<?xml version="1.0" encoding="utf-8" ?>
<dwsync>
<file name="_comentario.php" server="31.170.167.196//public_html/" local="130113801625148835" remote="130077456000000000" Dst="0" />
<file name="_form.php" server="31.170.167.196//public_html/" local="130113801625238840" remote="130077456000000000" Dst="0" />
<file name="_search.php" server="31.170.167.196//public_html/" local="130113801647500114" remote="130077456000000000" Dst="0" />
<file name="_view.php" server="31.170.167.196//public_html/" local="130113801647470112" remote="130077456000000000" Dst="0" />
<file name="admin.php" server="31.170.167.196//public_html/" local="130113801658310732" remote="130077456000000000" Dst="0" />
<file name="create.php" server="31.170.167.196//public_html/" local="130113801658150723" remote="130077456600000000" Dst="0" />
<file name="index.php" server="31.170.167.196//public_html/" local="130113801674351650" remote="130077456600000000" Dst="0" />
<file name="update.php" server="31.170.167.196//public_html/" local="130113801674361650" remote="130077456600000000" Dst="0" />
<file name="view.php" server="31.170.167.196//public_html/" local="130113801674461656" remote="130077456600000000" Dst="0" />
<file name="votacion.php" server="31.170.167.196//public_html/" local="130113801688912482" remote="130077456600000000" Dst="0" />
</dwsync>